Metadata-Version: 2.1
Name: pandas_aprbot
Version: 1.5.3
Summary: Powerful data structures for data analysis, time series, and statistics
Home-page: https://github.com/aprbot/pandas
Author: The Pandas Development Team
Author-email: pandas-dev@python.org
License: BSD-3-Clause
Project-URL: Bug Tracker, https://github.com/pandas-dev/pandas/issues
Project-URL: Documentation, https://pandas.pydata.org/docs/
Project-URL: Source Code, https://github.com/aprbot/pandas
Platform: any
Classifier: Development Status :: 5 - Production/Stable
Classifier: Environment :: Console
Classifier: Intended Audience :: Science/Research
Classifier: License :: OSI Approved :: BSD License
Classifier: Operating System :: OS Independent
Classifier: Programming Language :: Cython
Classifier: Programming Language :: Python
Classifier: Programming Language :: Python :: 3
Classifier: Programming Language :: Python :: 3 :: Only
Classifier: Programming Language :: Python :: 3.8
Classifier: Programming Language :: Python :: 3.9
Classifier: Programming Language :: Python :: 3.10
Classifier: Programming Language :: Python :: 3.11
Classifier: Topic :: Scientific/Engineering
Requires-Python: >=3.8
License-File: LICENSE
Requires-Dist: python-dateutil>=2.8.1
Requires-Dist: pytz>=2020.1
Requires-Dist: numpy>=1.20.3; python_version < "3.10"
Requires-Dist: numpy>=1.21.0; python_version >= "3.10"
Requires-Dist: numpy>=1.23.2; python_version >= "3.11"
Provides-Extra: test
Requires-Dist: hypothesis>=5.5.3; extra == "test"
Requires-Dist: pytest>=6.0; extra == "test"
Requires-Dist: pytest-xdist>=1.31; extra == "test"
